dcm2niiw/__init__.py
dcm2niiw/__main__.py
dcm2niiw/defaults.py
dcm2niiw/enums.py
dcm2niiw/headers.py
dcm2niiw/py.typed
dcm2niiw/wrapper.py
dcm2niiw-0.1.5.dist-info/WHEEL
dcm2niiw-0.1.5.dist-info/entry_points.txt
dcm2niiw-0.1.5.dist-info/METADATA
dcm2niiw-0.1.5.dist-info/RECORD
