Metadata-Version: 2.3
Name: dcm2niiw
Version: 0.1.5
Summary: Thin dcm2niix wrapper with Python and CLI interfaces.
Author: Fernando Pérez-García
Author-email: Fernando Pérez-García <fepegar@gmail.com>
Requires-Dist: dcm2niix
Requires-Dist: loguru
Requires-Dist: pydicom
Requires-Dist: tqdm
Requires-Dist: typer
Requires-Python: >=3.9
